<?xml version="1.0" ?>
<SmellBaseline>
  <ManuallySuppressedIssues></ManuallySuppressedIssues>
  <CurrentIssues>
    <ID>EmptyFunctionBlock:SinglePartScreenView.kt${ }</ID>
    <ID>MagicNumber:Color.kt$0xFF03DAC5</ID>
    <ID>MagicNumber:Color.kt$0xFF3700B3</ID>
    <ID>MagicNumber:Color.kt$0xFF6200EE</ID>
    <ID>MagicNumber:Color.kt$0xFFBB86FC</ID>
    <ID>TooGenericExceptionCaught:PartRepository.kt$PartRepository$e: Exception</ID>
    <ID>UnusedPrivateMember:ApiService.kt$ApiService$config: RemoteConfigInterface</ID>
    <ID>UnusedPrivateMember:SinglePartScreenView.kt$onSearchChange: (String) -&gt; Unit</ID>
    <ID>UnusedPrivateMember:SinglePartScreenView.kt$parts: List&lt;PartResponse&gt;?</ID>
  </CurrentIssues>
</SmellBaseline>
